MANIFEST.in
README.md
setup.cfg
setup.py
easycms/__init__.py
easycms/accesscontrol.py
easycms/cmsutil.py
easycms/comments.py
easycms/constants.py
easycms/datautil.py
easycms/editor.py
easycms/forms.py
easycms/migration.py
easycms/models.py
easycms/rssfeed.py
easycms/settings.py
easycms/urls.py
easycms.egg-info/PKG-INFO
easycms.egg-info/SOURCES.txt
easycms.egg-info/dependency_links.txt
easycms.egg-info/requires.txt
easycms.egg-info/top_level.txt
easycms/customfields/__init__.py
easycms/customfields/customfields.py
easycms/customfields/env.py
easycms/customfields/templates/anti_spam_field.html
easycms/customfields/templates/ef_basic_input.html
easycms/customfields/templates/ef_macros.html
easycms/customfields/templates/publish_field.html
easycms/static/ckeditor/CHANGES.md
easycms/static/ckeditor/LICENSE.md
easycms/static/ckeditor/README.md
easycms/static/ckeditor/build-config.js
easycms/static/ckeditor/ckeditor.js
easycms/static/ckeditor/config.js
easycms/static/ckeditor/contents.css
easycms/static/ckeditor/styles.js
easycms/static/ckeditor/adapters/jquery.js
easycms/static/ckeditor/lang/en.js
easycms/static/ckeditor/plugins/icons.png
easycms/static/ckeditor/plugins/icons_hidpi.png
easycms/static/ckeditor/plugins/a11yhelp/dialogs/a11yhelp.js
easycms/static/ckeditor/plugins/a11yhelp/dialogs/lang/_translationstatus.txt
easycms/static/ckeditor/plugins/a11yhelp/dialogs/lang/af.js
easycms/static/ckeditor/plugins/a11yhelp/dialogs/lang/ar.js
easycms/static/ckeditor/plugins/a11yhelp/dialogs/lang/az.js
easycms/static/ckeditor/plugins/a11yhelp/dialogs/lang/bg.js
easycms/static/ckeditor/plugins/a11yhelp/dialogs/lang/ca.js
easycms/static/ckeditor/plugins/a11yhelp/dialogs/lang/cs.js
easycms/static/ckeditor/plugins/a11yhelp/dialogs/lang/cy.js
easycms/static/ckeditor/plugins/a11yhelp/dialogs/lang/da.js
easycms/static/ckeditor/plugins/a11yhelp/dialogs/lang/de-ch.js
easycms/static/ckeditor/plugins/a11yhelp/dialogs/lang/de.js
easycms/static/ckeditor/plugins/a11yhelp/dialogs/lang/el.js
easycms/static/ckeditor/plugins/a11yhelp/dialogs/lang/en-au.js
easycms/static/ckeditor/plugins/a11yhelp/dialogs/lang/en-gb.js
