Metadata-Version: 1.1
Name: easycms
Version: 0.3.8
Summary: CMS and Blogging Sysetm for Flask
Home-page: https://github.com/stevelittlefish/easycms
Author: Stephen Brown (Little Fish Solutions LTD)
Author-email: opensource@littlefish.solutions
License: LGPLv3
Download-URL: https://github.com/stevelittlefish/easycms/archive/v0.3.8.tar.gz
Keywords: flask,jinja2,easy,cms,blog
Platform: UNKNOWN
Classifier: License :: OSI Approved :: GNU Lesser General Public License v3 (LGPLv3)
Classifier: Framework :: Flask
Classifier: Development Status :: 5 - Production/Stable
Classifier: Intended Audience :: Developers
Classifier: Programming Language :: Python :: 3
Classifier: Topic :: Software Development :: Libraries
